Metadata-Version: 1.1
Name: domus
Version: 0.0.0
Summary: 
Home-page: https://gitlab.com/bartfrenk/miniscule/
Author: Bart Frenk
Author-email: bart.frenk@gmail.com
License: UNKNOWN
Keywords: configuration
Platform: UNKNOWN
Classifier: Programming Language :: Python :: 3
Classifier: License :: OSI Approved :: MIT License
Classifier: Operating System :: OS Independent
Classifier: Programming Language :: Python :: 3
